stacks_contentgroup/__init__.py
stacks_contentgroup/admin.py
stacks_contentgroup/apps.py
stacks_contentgroup/models.py
stacks_contentgroup/serializers.py
stacks_contentgroup/stuff.py
stacks_contentgroup/migrations/0001_initial.py
stacks_contentgroup/migrations/0002_auto_20150528_1526.py
stacks_contentgroup/migrations/0003_auto_20150528_1526.py
stacks_contentgroup/migrations/0004_auto_20150529_2033.py
stacks_contentgroup/migrations/__init__.py
stacks_contentgroup/static/js/stacks_contentgroup.js
stacks_contentgroup/static/sass/_stacks_contentgroup.scss
stacks_contentgroup/templates/stacks_contentgroup/contentgroup/contentgroup-2up.html
stacks_contentgroup/templates/stacks_contentgroup/contentgroup/contentgroup-3up.html
stacks_contentgroup-0.1.2.dist-info/DESCRIPTION.rst
stacks_contentgroup-0.1.2.dist-info/LICENSE.txt
stacks_contentgroup-0.1.2.dist-info/METADATA
stacks_contentgroup-0.1.2.dist-info/metadata.json
stacks_contentgroup-0.1.2.dist-info/RECORD
stacks_contentgroup-0.1.2.dist-info/top_level.txt
stacks_contentgroup-0.1.2.dist-info/WHEEL
tests/__init__.py
tests/test_settings.py
tests/tests.py
tests/urls.py
